zope.preference-5.0-py3.9-nspkg.pth
zope/preference/README.rst
zope/preference/__init__.py
zope/preference/configure.zcml
zope/preference/default.py
zope/preference/interfaces.py
zope/preference/meta.zcml
zope/preference/metaconfigure.py
zope/preference/metadirectives.py
zope/preference/preference.py
zope/preference/tests.py
zope.preference-5.0.dist-info/LICENSE.txt
zope.preference-5.0.dist-info/METADATA
zope.preference-5.0.dist-info/WHEEL
zope.preference-5.0.dist-info/namespace_packages.txt
zope.preference-5.0.dist-info/top_level.txt
zope.preference-5.0.dist-info/RECORD
