Metadata-Version: 2.1
Name: zope.preference
Version: 5.0
Summary: User Preferences Framework
Home-page: http://github.com/zopefoundation/zope.preference
Author: Zope Foundation and Contributors
Author-email: zope-dev@zope.dev
License: ZPL 2.1
Keywords: bluebream zope zope3 user preference
Classifier: Development Status :: 5 - Production/Stable
Classifier: Environment :: Web Environment
Classifier: Intended Audience :: Developers
Classifier: License :: OSI Approved :: Zope Public License
Classifier: Programming Language :: Python
Classifier: Programming Language :: Python :: 3
Classifier: Programming Language :: Python :: 3.7
Classifier: Programming Language :: Python :: 3.8
Classifier: Programming Language :: Python :: 3.9
Classifier: Programming Language :: Python :: 3.10
Classifier: Programming Language :: Python :: 3.11
Classifier: Programming Language :: Python :: Implementation :: CPython
Classifier: Programming Language :: Python :: Implementation :: PyPy
Classifier: Natural Language :: English
Classifier: Operating System :: OS Independent
Classifier: Topic :: Internet :: WWW/HTTP
Classifier: Framework :: Zope :: 3
Requires-Python: >=3.7
License-File: LICENSE.txt
Requires-Dist: setuptools
Requires-Dist: BTrees
Requires-Dist: zope.annotation
Requires-Dist: zope.component (>=3.8.0)
Requires-Dist: zope.container
Requires-Dist: zope.schema
Requires-Dist: zope.security
Requires-Dist: zope.traversing
Provides-Extra: test
Requires-Dist: zope.security ; extra == 'test'
Requires-Dist: zope.site ; extra == 'test'
Requires-Dist: zope.testing ; extra == 'test'
Requires-Dist: zope.testrunner ; extra == 'test'
Provides-Extra: zcml
Requires-Dist: zope.security ; extra == 'zcml'
